kekas/__init__.py
kekas/callbacks.py
kekas/data.py
kekas/keker.py
kekas/metrics.py
kekas/modules.py
kekas/state.py
kekas/transformations.py
kekas/utils.py
kekas-0.1.dist-info/LICENSE
kekas-0.1.dist-info/METADATA
kekas-0.1.dist-info/WHEEL
kekas-0.1.dist-info/top_level.txt
kekas-0.1.dist-info/RECORD
